{
    "results": {
        "GetValue": {
            "adv.upnp.osname": {
                "keywords": [],
                "1": {
                    "\u0000": [
                        "0xc0e8"
                    ]
                }
            },
            "adv.upnp.manufacturer": {
                "keywords": [],
                "1": {
                    "\u0000": [
                        "0xc24c"
                    ]
                }
            },
            "adv.upnp.osversion": {
                "keywords": [],
                "1": {
                    "\u0000": [
                        "0xc154"
                    ]
                }
            },
            "adv.upnp.description": {
                "keywords": [],
                "1": {
                    "\u0000": [
                        "0xc2b8"
                    ]
                }
            },
            "adv.upnp.version": {
                "keywords": [],
                "1": {
                    "\u0000": [
                        "0xc07c"
                    ]
                }
            },
            "lan.ip": {
                "keywords": [],
                "1": {
                    "\u0000": [
                        "0xc1bc"
                    ]
                }
            }
        }
    },
    "name": "miniupnpd",
    "path": "/home/mdf/FirmSieve/stage1/firm/Tenda/analyzed/_US_AC15V1.0BR_V15.03.05.18_multi_TD01.bin.extracted/squashfs-root/bin/miniupnpd",
    "error": null,
    "cfg_time": 5.473200082778931,
    "vra_time": 41.83593463897705,
    "analysis_time": 0,
    "has_sinks": true,
    "sink_times": {
        "GetValue": 1.2547545433044434
    },
    "sha256": "6e7c82ee60946601e00c1972314ff2d4a9f8dcbd20e2bc78689e7d05d43a854a"
}